README.txt
freshpick.zip
setup.py
docs/HISTORY.txt
docs/INSTALL.txt
docs/LICENSE.GPL
docs/LICENSE.txt
plonetheme/__init__.py
plonetheme.freshpick.egg-info/PKG-INFO
plonetheme.freshpick.egg-info/SOURCES.txt
plonetheme.freshpick.egg-info/dependency_links.txt
plonetheme.freshpick.egg-info/entry_points.txt
plonetheme.freshpick.egg-info/namespace_packages.txt
plonetheme.freshpick.egg-info/not-zip-safe
plonetheme.freshpick.egg-info/requires.txt
plonetheme.freshpick.egg-info/top_level.txt
plonetheme/freshpick/__init__.py
plonetheme/freshpick/configure.zcml
plonetheme/freshpick/tests.py
plonetheme/freshpick/theme/freshpick/index.html
plonetheme/freshpick/theme/freshpick/rules.xml
plonetheme/freshpick/theme/freshpick/static/css/FreshPick.css
plonetheme/freshpick/theme/freshpick/static/css/reset.css
plonetheme/freshpick/theme/freshpick/static/css/screen.css
plonetheme/freshpick/theme/freshpick/static/images/bg.gif
plonetheme/freshpick/theme/freshpick/static/images/current.gif
plonetheme/freshpick/theme/freshpick/static/images/dotted-lines.gif
plonetheme/freshpick/theme/freshpick/static/images/firefox-gray.jpg
plonetheme/freshpick/theme/freshpick/static/images/gravatar.jpg
plonetheme/freshpick/theme/freshpick/static/images/header-bg.png
plonetheme/freshpick/theme/freshpick/static/images/header-search.gif
plonetheme/freshpick/theme/freshpick/static/images/hor-line.gif
plonetheme/freshpick/theme/freshpick/static/images/img-featured.jpg
plonetheme/freshpick/theme/freshpick/static/images/img-post.jpg
plonetheme/freshpick/theme/freshpick/static/images/quote.gif
plonetheme/freshpick/theme/freshpick/static/images/search.gif
plonetheme/freshpick/theme/freshpick/static/images/thumb.jpg