Metadata-Version: 1.0
Name: plonetheme.freshpick
Version: 0.1.0
Summary: An installable Diazo theme for Plone 4.1
Home-page: https://github.com/collective/plonetheme.freshpick
Author: Alex Clark
Author-email: aclark@aclark.net
License: Creative Commons Attribution-ShareAlike 3.0 Unported License.
Platform: UNKNOWN
Classifier: Framework :: Plone
Classifier: Programming Language :: Python
